<?xml version="1.0" encoding="utf-8" standalone="yes"?>
<AutomationSequence documentVersion="1.0">
  <Macros>
    <Macro Name="regionToDownload" Value="na"/>
    <Macro Name="regionCaps" Value="NA"/>
  </Macros>
  <TaskDefinitions>
    <!-- import macros -->
    <Task ID="import_macros" Command="import_macro" RepoUrlPath="Macro_templates/ClanIcons.xml"/>
    <!-- import tasks -->
    <Task ID="import_tasks" Command="import_task" RepoUrlPath="Task_templates/ClanIcons.xml"/>
  </TaskDefinitions>
</AutomationSequence>